dummylog.py
dummylog-0.0.4.dist-info/LICENSE
dummylog-0.0.4.dist-info/METADATA
dummylog-0.0.4.dist-info/WHEEL
dummylog-0.0.4.dist-info/top_level.txt
dummylog-0.0.4.dist-info/RECORD
