Metadata-Version: 2.1
Name: dummylog
Version: 0.0.4
Summary: dummylog is the open source python package to help the python module/plugin developers to create/update the log files in simple syntax and easy format
Home-page: https://github.com/selva221724/dummylog
Author: Tamil Selvan A V
License: MIT
Platform: UNKNOWN
Classifier: Programming Language :: Python :: 3
Classifier: License :: OSI Approved :: MIT License
Classifier: Framework :: IPython
Classifier: Operating System :: Microsoft :: Windows :: Windows 10
Classifier: Intended Audience :: Science/Research
Classifier: Intended Audience :: Developers
Classifier: Topic :: Scientific/Engineering
Classifier: Environment :: Console
Requires-Python: >=3.6
License-File: LICENSE
